logreader
ui
