Metadata-Version: 1.1
Name: zipnish
Version: 0.1.5
Summary: zipnish
Home-page: https://github.com/varnish/zipnish.git
Author: Marius Magureanu
Author-email: marius@varnish-software.com
License: Apache License 2.0
Platform: Linux
Classifier: Development Status :: 4 - Beta
Classifier: Intended Audience :: Developers
Classifier: License :: OSI Approved :: Apache Software License
Classifier: Programming Language :: Python :: 2.7
